[
    {
        "groupName": "শ্যাম স্টিল",
        "itemList": [
            {
                "itemId": "shyam_pati",
                "itemName": "শ্যামের পাতি",
                "currentPrice": "98",
                "lastPrice": "95",
                "stock": "200",
                "unit": "KG"
            },
            {
                "itemId": "shyam_z",
                "itemName": "শ্যামের Z",
                "currentPrice": "98",
                "lastPrice": "95",
                "stock": "200",
                "unit": "KG"
            },
            {
                "itemId": "shyam_angle",
                "itemName": "শ্যামের এঙ্গেল",
                "currentPrice": "98",
                "lastPrice": "95",
                "stock": "200",
                "unit": "KG"
            },
            {
                "itemId": "shyam_bar_7",
                "itemName": "শ্যামের বার (7)",
                "currentPrice": "98",
                "lastPrice": "95",
                "stock": "200",
                "unit": "KG"
            },
            {
                "itemId": "shyam_bar_10",
                "itemName": "শ্যামের বার (10)",
                "currentPrice": "98",
                "lastPrice": "95",
                "stock": "200",
                "unit": "KG"
            },
            {
                "itemId": "shyam_bar_12",
                "itemName": "শ্যামের বার (12)",
                "currentPrice": "98",
                "lastPrice": "95",
                "stock": "200",
                "unit": "KG"
            }
        ]
    },
    {
        "groupName": "SRMB স্টিল",
        "itemList": [
            {
                "itemId": "srmb_pati",
                "itemName": "SRMB পাতি",
                "currentPrice": "96",
                "lastPrice": "95",
                "stock": "300",
                "unit": "KG"
            },
            {
                "itemId": "srmb_angle",
                "itemName": "SRMB এঙ্গেল",
                "currentPrice": "98",
                "lastPrice": "95",
                "stock": "200",
                "unit": "KG"
            }
        ]
    },
    {
        "groupName": "লোকাল স্টিল",
        "itemList": [
            {
                "itemId": "local_pati",
                "itemName": "লোকাল পাতি",
                "currentPrice": "78",
                "lastPrice": "73",
                "stock": "500",
                "unit": "KG"
            },
            {
                "itemId": "local_angle",
                "itemName": "লোকাল এঙ্গেল",
                "currentPrice": "78",
                "lastPrice": "73",
                "stock": "500",
                "unit": "KG"
            },
            {
                "itemId": "local_bar_7",
                "itemName": "লোকাল বার (7)",
                "currentPrice": "78",
                "lastPrice": "73",
                "stock": "500",
                "unit": "KG"
            },
            {
                "itemId": "local_z",
                "itemName": "লোকাল Z",
                "currentPrice": "78",
                "lastPrice": "73",
                "stock": "500",
                "unit": "KG"
            }
        ]
    },
    {
        "groupName": "অন্যান্য সামগ্রী",
        "itemList": [
            {
                "itemId": "channel",
                "itemName": "চ্যানেল",
                "currentPrice": "87",
                "lastPrice": "77",
                "stock": "150",
                "unit": "KG"
            }
        ]
    }
]